{
	"texture_size": [256, 256],
	"textures": {
		"0": "brimstone:entity/redstone_monster/redstone_golem",
		"particle": "brimstone:entity/redstone_monster/redstone_golem"
	},
	"elements": [
		{
			"name": "pelvis",
			"from": [2.70313, 1, 4.86523],
			"to": [13.70313, 5, 11.86523],
			"rotation": {"angle": 0, "axis": "y", "origin": [8.20313, -9, 8.36523]},
			"faces": {
				"north": {"uv": [8.375, 3.125, 9.75, 3.625], "texture": "#0"},
				"east": {"uv": [7.5, 3.125, 8.375, 3.625], "texture": "#0"},
				"south": {"uv": [10.625, 3.125, 12, 3.625], "texture": "#0"},
				"west": {"uv": [9.75, 3.125, 10.625, 3.625], "texture": "#0"},
				"up": {"uv": [9.75, 3.125, 8.375, 2.25], "texture": "#0"},
				"down": {"uv": [11.125, 2.25, 9.75, 3.125], "texture": "#0"}
			}
		},
		{
			"name": "body",
			"from": [-1.79687, 5, 3.36523],
			"to": [18.20313, 21, 13.36523],
			"rotation": {"angle": 0, "axis": "y", "origin": [8.20313, -9, 8.36523]},
			"faces": {
				"north": {"uv": [1.25, 1.25, 3.75, 3.25], "texture": "#0"},
				"east": {"uv": [0, 1.25, 1.25, 3.25], "texture": "#0"},
				"south": {"uv": [5, 1.25, 7.5, 3.25], "texture": "#0"},
				"west": {"uv": [3.75, 1.25, 5, 3.25], "texture": "#0"},
				"up": {"uv": [3.75, 1.25, 1.25, 0], "texture": "#0"},
				"down": {"uv": [6.25, 0, 3.75, 1.25], "texture": "#0"}
			}
		},
		{
			"name": "body",
			"from": [4.20313, 7, 8.36523],
			"to": [12.20313, 15, 16.36523],
			"rotation": {"angle": 0, "axis": "y", "origin": [8.20313, -9, 8.36523]},
			"faces": {
				"north": {"uv": [4.0625, 6.625, 5.0625, 7.625], "texture": "#0"},
				"east": {"uv": [3.0625, 6.625, 4.0625, 7.625], "texture": "#0"},
				"south": {"uv": [6.0625, 6.625, 7.0625, 7.625], "texture": "#0"},
				"west": {"uv": [5.0625, 6.625, 6.0625, 7.625], "texture": "#0"},
				"up": {"uv": [5.0625, 6.625, 4.0625, 5.625], "texture": "#0"},
				"down": {"uv": [6.0625, 5.625, 5.0625, 6.625], "texture": "#0"}
			}
		},
		{
			"name": "head",
			"from": [4.20313, 13, -2.63477],
			"to": [12.20313, 21, 3.36523],
			"rotation": {"angle": 0, "axis": "y", "origin": [8.20313, -9, 8.36523]},
			"faces": {
				"north": {"uv": [8.5, 1.25, 9.5, 2.25], "texture": "#0"},
				"east": {"uv": [7.75, 1.25, 8.5, 2.25], "texture": "#0"},
				"south": {"uv": [10.25, 1.25, 11.25, 2.25], "texture": "#0"},
				"west": {"uv": [9.5, 1.25, 10.25, 2.25], "texture": "#0"},
				"up": {"uv": [9.5, 1.25, 8.5, 0.5], "texture": "#0"},
				"down": {"uv": [10.5, 0.5, 9.5, 1.25], "texture": "#0"}
			}
		},
		{
			"name": "hand1",
			"from": [-8.79687, 8, 5.36523],
			"to": [-1.79687, 20, 11.36523],
			"rotation": {"angle": 0, "axis": "y", "origin": [-18.79687, -9, 8.36523]},
			"faces": {
				"north": {"uv": [0.75, 4, 1.625, 5.5], "texture": "#0"},
				"east": {"uv": [0, 4, 0.75, 5.5], "texture": "#0"},
				"south": {"uv": [2.375, 4, 3.25, 5.5], "texture": "#0"},
				"west": {"uv": [1.625, 4, 2.375, 5.5], "texture": "#0"},
				"up": {"uv": [1.625, 4, 0.75, 3.25], "texture": "#0"},
				"down": {"uv": [2.5, 3.25, 1.625, 4], "texture": "#0"}
			}
		},
		{
			"name": "hand2",
			"from": [-9.79687, -3, 5.36523],
			"to": [-4.29687, 8, 11.36523],
			"shade": false,
			"rotation": {"angle": 0, "axis": "y", "origin": [6.32813, 2.3125, 8.72461]},
			"faces": {
				"north": {"uv": [4.875, 8.5, 4.1875, 9.875], "texture": "#0"},
				"east": {"uv": [5.625, 8.5, 4.875, 9.875], "texture": "#0"},
				"south": {"uv": [6.3125, 8.5, 5.625, 9.875], "texture": "#0"},
				"west": {"uv": [4.1875, 8.5, 3.4375, 9.875], "texture": "#0"},
				"up": {"uv": [4.1875, 8.5, 4.875, 7.75], "texture": "#0"},
				"down": {"uv": [4.875, 7.75, 5.5625, 8.5], "texture": "#0"}
			}
		},
		{
			"name": "finger1",
			"from": [-8.79687, -8, 8.36523],
			"to": [-7.29687, -3, 10.86523],
			"shade": false,
			"rotation": {"angle": 0, "axis": "y", "origin": [7.32813, 2.3125, 8.72461]},
			"faces": {
				"north": {"uv": [6.5625, 3.75, 6.375, 4.375], "texture": "#0"},
				"east": {"uv": [6.875, 3.75, 6.5625, 4.375], "texture": "#0"},
				"south": {"uv": [7.0625, 3.75, 6.875, 4.375], "texture": "#0"},
				"west": {"uv": [6.375, 3.75, 6.0625, 4.375], "texture": "#0"},
				"up": {"uv": [6.375, 3.75, 6.5625, 3.4375], "texture": "#0"},
				"down": {"uv": [6.5625, 3.4375, 6.75, 3.75], "texture": "#0"}
			}
		},
		{
			"name": "finger2",
			"from": [-8.79687, -8, 5.49023],
			"to": [-7.29687, -3, 7.99023],
			"shade": false,
			"rotation": {"angle": 0, "axis": "y", "origin": [7.32813, 2.3125, 8.72461]},
			"faces": {
				"north": {"uv": [6.5625, 3.75, 6.375, 4.375], "texture": "#0"},
				"east": {"uv": [6.875, 3.75, 6.5625, 4.375], "texture": "#0"},
				"south": {"uv": [7.0625, 3.75, 6.875, 4.375], "texture": "#0"},
				"west": {"uv": [6.375, 3.75, 6.0625, 4.375], "texture": "#0"},
				"up": {"uv": [6.375, 3.75, 6.5625, 3.4375], "texture": "#0"},
				"down": {"uv": [6.5625, 3.4375, 6.75, 3.75], "texture": "#0"}
			}
		},
		{
			"name": "finger3",
			"from": [-6.17187, -7, 8.36523],
			"to": [-4.67187, -3, 10.86523],
			"shade": false,
			"rotation": {"angle": 0, "axis": "y", "origin": [9.07813, 2.3125, 8.72461]},
			"faces": {
				"north": {"uv": [5.5625, 3.875, 5.375, 4.375], "texture": "#0"},
				"east": {"uv": [5.875, 3.875, 5.5625, 4.375], "texture": "#0"},
				"south": {"uv": [6.0625, 3.875, 5.875, 4.375], "texture": "#0"},
				"west": {"uv": [5.375, 3.875, 5.0625, 4.375], "texture": "#0"},
				"up": {"uv": [5.375, 3.875, 5.5625, 3.5625], "texture": "#0"},
				"down": {"uv": [5.5625, 3.5625, 5.75, 3.875], "texture": "#0"}
			}
		},
		{
			"name": "hand3",
			"from": [18.45313, 8, 4.64648],
			"to": [25.45313, 20, 10.64648],
			"rotation": {"angle": 0, "axis": "y", "origin": [8.32813, 2.3125, 8.00586]},
			"faces": {
				"north": {"uv": [0.9375, 8.375, 1.8125, 9.875], "texture": "#0"},
				"east": {"uv": [0.1875, 8.375, 0.9375, 9.875], "texture": "#0"},
				"south": {"uv": [2.5625, 8.375, 3.4375, 9.875], "texture": "#0"},
				"west": {"uv": [1.8125, 8.375, 2.5625, 9.875], "texture": "#0"},
				"up": {"uv": [1.8125, 8.375, 0.9375, 7.625], "texture": "#0"},
				"down": {"uv": [2.6875, 7.625, 1.8125, 8.375], "texture": "#0"}
			}
		},
		{
			"name": "hand4",
			"from": [20.95313, -3, 4.64648],
			"to": [26.45313, 8, 10.64648],
			"rotation": {"angle": 0, "axis": "y", "origin": [8.07813, 2.3125, 8.00586]},
			"faces": {
				"north": {"uv": [4.1875, 8.5, 4.875, 9.875], "texture": "#0"},
				"east": {"uv": [3.4375, 8.5, 4.1875, 9.875], "texture": "#0"},
				"south": {"uv": [5.625, 8.5, 6.3125, 9.875], "texture": "#0"},
				"west": {"uv": [4.875, 8.5, 5.625, 9.875], "texture": "#0"},
				"up": {"uv": [4.875, 8.5, 4.1875, 7.75], "texture": "#0"},
				"down": {"uv": [5.5625, 7.75, 4.875, 8.5], "texture": "#0"}
			}
		},
		{
			"name": "finger4",
			"from": [23.95313, -8, 7.64648],
			"to": [25.45313, -3, 10.14648],
			"rotation": {"angle": 0, "axis": "y", "origin": [8.07813, 2.3125, 8.00586]},
			"faces": {
				"north": {"uv": [6.375, 3.75, 6.5625, 4.375], "texture": "#0"},
				"east": {"uv": [6.0625, 3.75, 6.375, 4.375], "texture": "#0"},
				"south": {"uv": [6.875, 3.75, 7.0625, 4.375], "texture": "#0"},
				"west": {"uv": [6.5625, 3.75, 6.875, 4.375], "texture": "#0"},
				"up": {"uv": [6.5625, 3.75, 6.375, 3.4375], "texture": "#0"},
				"down": {"uv": [6.75, 3.4375, 6.5625, 3.75], "texture": "#0"}
			}
		},
		{
			"name": "finger5",
			"from": [23.95313, -8, 4.77148],
			"to": [25.45313, -3, 7.27148],
			"rotation": {"angle": 0, "axis": "y", "origin": [8.07813, 2.3125, 8.00586]},
			"faces": {
				"north": {"uv": [6.375, 3.75, 6.5625, 4.375], "texture": "#0"},
				"east": {"uv": [6.0625, 3.75, 6.375, 4.375], "texture": "#0"},
				"south": {"uv": [6.875, 3.75, 7.0625, 4.375], "texture": "#0"},
				"west": {"uv": [6.5625, 3.75, 6.875, 4.375], "texture": "#0"},
				"up": {"uv": [6.5625, 3.75, 6.375, 3.4375], "texture": "#0"},
				"down": {"uv": [6.75, 3.4375, 6.5625, 3.75], "texture": "#0"}
			}
		},
		{
			"name": "finger6",
			"from": [21.57813, -7, 7.64648],
			"to": [23.07813, -3, 10.14648],
			"shade": false,
			"rotation": {"angle": 0, "axis": "y", "origin": [8.07813, 2.3125, 8.00586]},
			"faces": {
				"north": {"uv": [5.5625, 3.875, 5.375, 4.375], "texture": "#0"},
				"east": {"uv": [5.875, 3.875, 5.5625, 4.375], "texture": "#0"},
				"south": {"uv": [6.0625, 3.875, 5.875, 4.375], "texture": "#0"},
				"west": {"uv": [5.375, 3.875, 5.0625, 4.375], "texture": "#0"},
				"up": {"uv": [5.375, 3.875, 5.5625, 3.5625], "texture": "#0"},
				"down": {"uv": [5.5625, 3.5625, 5.75, 3.875], "texture": "#0"}
			}
		},
		{
			"name": "leg2",
			"from": [-1.79687, -9, 5.36523],
			"to": [4.20313, 1, 11.36523],
			"rotation": {"angle": 0, "axis": "y", "origin": [8.20313, -9, 8.36523]},
			"faces": {
				"north": {"uv": [10.8125, 4.375, 11.5625, 5.625], "texture": "#0"},
				"east": {"uv": [10.0625, 4.375, 10.8125, 5.625], "texture": "#0"},
				"south": {"uv": [12.3125, 4.375, 13.0625, 5.625], "texture": "#0"},
				"west": {"uv": [11.5625, 4.375, 12.3125, 5.625], "texture": "#0"},
				"up": {"uv": [11.5625, 4.375, 10.8125, 3.625], "texture": "#0"},
				"down": {"uv": [12.3125, 3.625, 11.5625, 4.375], "texture": "#0"}
			}
		},
		{
			"name": "leg1",
			"from": [12.20313, -9, 5.36523],
			"to": [18.20313, 1, 11.36523],
			"rotation": {"angle": 0, "axis": "y", "origin": [8.20313, -9, 8.36523]},
			"faces": {
				"north": {"uv": [7.8125, 4.375, 8.5625, 5.625], "texture": "#0"},
				"east": {"uv": [7.0625, 4.375, 7.8125, 5.625], "texture": "#0"},
				"south": {"uv": [9.3125, 4.375, 10.0625, 5.625], "texture": "#0"},
				"west": {"uv": [8.5625, 4.375, 9.3125, 5.625], "texture": "#0"},
				"up": {"uv": [8.5625, 4.375, 7.8125, 3.625], "texture": "#0"},
				"down": {"uv": [9.3125, 3.625, 8.5625, 4.375], "texture": "#0"}
			}
		}
	],
	"groups": [
		{
			"name": "redstonegolem",
			"origin": [0, 0, 0],
			"children": [
				{
					"name": "pelvis",
					"origin": [0, 5, 0],
					"children": [0,
						{
							"name": "body",
							"origin": [0, 4.9, 0.8],
							"children": [1, 2,
								{
									"name": "head",
									"origin": [0, 17, -5],
									"children": [3]
								},
								{
									"name": "hand1",
									"origin": [9.75, 16, 0],
									"children": [4,
										{
											"name": "hand2",
											"origin": [16, 7.875, 0],
											"children": [5,
												{
													"name": "finger1",
													"origin": [17, -3, -1.25],
													"children": [6]
												},
												{
													"name": "finger2",
													"origin": [17, -3, 1.625],
													"children": [7]
												},
												{
													"name": "finger3",
													"origin": [14.625, -3.5, -1.25],
													"children": [8]
												}
											]
										}
									]
								},
								{
									"name": "hand3",
									"origin": [-10, 16, 0],
									"children": [9,
										{
											"name": "hand4",
											"origin": [-15.75, 8, 0],
											"children": [10,
												{
													"name": "finger4",
													"origin": [-16.5, -3.5, -1.25],
													"children": [11]
												},
												{
													"name": "finger5",
													"origin": [-16.5, -3, 1.625],
													"children": [12]
												},
												{
													"name": "finger6",
													"origin": [-14.125, -3, -1.25],
													"children": [13]
												}
											]
										}
									]
								}
							]
						}
					]
				},
				{
					"name": "leg2",
					"origin": [-7, 1, 0],
					"children": [14]
				},
				{
					"name": "leg1",
					"origin": [7, 1, 0],
					"children": [15]
				}
			]
		}
	]
}